MANIFEST.in
README.rst
VERSION
setup.py
hitchrun/__init__.py
hitchrun/commandline.py
hitchrun/decorators.py
hitchrun/key_file.py
hitchrun/maintenance.py
hitchrun/packages.py
hitchrun.egg-info/PKG-INFO
hitchrun.egg-info/SOURCES.txt
hitchrun.egg-info/dependency_links.txt
hitchrun.egg-info/entry_points.txt
hitchrun.egg-info/not-zip-safe
hitchrun.egg-info/requires.txt
hitchrun.egg-info/top_level.txt